karrio/mappers/sf_express/__init__.py
karrio/mappers/sf_express/mapper.py
karrio/mappers/sf_express/proxy.py
karrio/mappers/sf_express/settings.py
karrio/providers/sf_express/__init__.py
karrio/providers/sf_express/error.py
karrio/providers/sf_express/tracking.py
karrio/providers/sf_express/units.py
karrio/providers/sf_express/utils.py
karrio.sf_express-2023.4.dist-info/METADATA
karrio.sf_express-2023.4.dist-info/WHEEL
karrio.sf_express-2023.4.dist-info/top_level.txt
karrio.sf_express-2023.4.dist-info/RECORD
