Metadata-Version: 2.1
Name: karrio.sf-express
Version: 2023.4
Summary: Karrio - SF-Express Shipping extension
Home-page: https://github.com/karrioapi/karrio
Author: karrio
Author-email: hello@karrio.io
License: Apache-2.0
Platform: UNKNOWN
Classifier: Intended Audience :: Developers
Classifier: Operating System :: OS Independent
Classifier: Programming Language :: Python :: 3
Requires-Dist: carrier.sf-express
Requires-Dist: karrio
